<?xml version="1.0" encoding="utf-8" ?>
<Items>
    <Item>
  		<Text>Administrator Home</Text>
	  	<Link>admin</Link>
    </Item>
    <Item>
      <Text>New User Requests</Text>
      <Link>admin/newUsers.aspx</Link>
    </Item>
    <Item>
      <Text>User Administration</Text>
      <Link>admin/users.aspx</Link>
    </Item>
    <Item>
      <Text>Competency Matrix Editor</Text>
      <Link>admin/editMatrix.aspx</Link>
    </Item>
  <Item>
    <Text>Application Settings</Text>
    <Link>admin/settings.aspx</Link>
  </Item>
</Items>